mypy_silent/__init__.py
mypy_silent/cli.py
mypy_silent/maho.py
mypy_silent/parser.py
mypy_silent/py.typed
mypy_silent/utils.py
mypy_silent-0.4.0.dist-info/entry_points.txt
mypy_silent-0.4.0.dist-info/LICENSE
mypy_silent-0.4.0.dist-info/WHEEL
mypy_silent-0.4.0.dist-info/METADATA
mypy_silent-0.4.0.dist-info/RECORD
