Metadata-Version: 2.1
Name: mypy-silent
Version: 0.4.0
Summary: Silence mypy by adding or removing code comments
License: MIT
Author: Wu Haotian
Author-email: whtsky@gmail.com
Requires-Python: >=3.6,<4.0
Classifier: License :: OSI Approved :: MIT License
Classifier: Programming Language :: Python :: 3
Classifier: Programming Language :: Python :: 3.10
Classifier: Programming Language :: Python :: 3.6
Classifier: Programming Language :: Python :: 3.7
Classifier: Programming Language :: Python :: 3.8
Classifier: Programming Language :: Python :: 3.9
Requires-Dist: typer (>=0.3.2,<0.4.0)
Requires-Dist: typing-extensions
